prsedm/__init__.py
prsedm/core/__init__.py
prsedm/core/bcf_parallel.py
prsedm/core/score_bcf.py
prsedm/core/scoring.py
prsedm/core/utilities.py
prsedm/core/variant_processing.py
prsedm/extensions/__init__.py
prsedm/extensions/grouped_scoring.py
prsedm/extensions/hla_int_grs.py
prsedm/extensions/score_dm.py
prsedm/extensions/JSON/prs_meta.json
prsedm/extensions/SQL/__init__.py
prsedm/extensions/SQL/get_dm_sql.py
prsedm-1.1.0.dist-info/licenses/LICENSE
prsedm-1.1.0.dist-info/METADATA
prsedm-1.1.0.dist-info/WHEEL
prsedm-1.1.0.dist-info/entry_points.txt
prsedm-1.1.0.dist-info/top_level.txt
prsedm-1.1.0.dist-info/RECORD
