Metadata-Version: 2.4
Name: prsedm
Version: 1.1.0
Summary: PRSedm (Polygenic Risk Score Extension for Diabetes Mellitus) is a package for local and remote generation of Polygenic Risk Scores (PRS) for Diabetes Mellitus (DM)
Author: Seth A. Sharp
Author-email: ssharp@stanford.edu
Requires-Python: >=3.9
License-File: LICENSE
Requires-Dist: joblib>=1.3
Requires-Dist: pandas>=2.2
Requires-Dist: pysam>=0.22
Dynamic: author
Dynamic: author-email
Dynamic: description
Dynamic: description-content-type
Dynamic: license-file
Dynamic: requires-dist
Dynamic: requires-python
Dynamic: summary
